tm/__init__.py
tm/__main__.py
tm/cli.py
tm/config.py
tm/run_recipe.py
tm/agents/models.py
tm/agents/registry.py
tm/agents/runtime.py
tm/agents/builtins/__init__.py
tm/agents/builtins/http_mock.py
tm/agents/builtins/noop.py
tm/agents/builtins/shell.py
tm/ai/__init__.py
tm/ai/controller.py
tm/ai/feedback.py
tm/ai/hooks.py
tm/ai/llm_client.py
tm/ai/mcp_bridge.py
tm/ai/observer.py
tm/ai/policy_adapter.py
tm/ai/policy_registry.py
tm/ai/policy_store.py
tm/ai/proposals.py
tm/ai/recorder_bridge.py
tm/ai/registry.py
tm/ai/retrospect.py
tm/ai/reward_config.py
tm/ai/run_pipeline.py
tm/ai/summarizer.py
tm/ai/plan/__init__.py
tm/ai/plan/schema.py
tm/ai/providers/__init__.py
tm/ai/providers/base.py
tm/ai/providers/fake.py
tm/ai/providers/openai.py
tm/ai/reflect/__init__.py
tm/ai/reflect/schema.py
tm/ai/tuner/__init__.py
tm/ai/tuner/bandit.py
tm/ai/tuner/base.py
tm/ana/__init__.py
tm/ana/planner.py
tm/ana/validator.py
tm/app/__init__.py
tm/app/demo_plan.py
tm/app/example_crud_flows.py
tm/app/flow_docs.py
tm/app/rich_demo_plan.py
tm/app/wiring.py
tm/app/wiring_ai.py
tm/app/wiring_flows.py
tm/app/wiring_service.py
tm/caps/__init__.py
tm/caps/catalog.py
tm/cli/artifacts_cli.py
tm/cli/caps.py
tm/cli/compose.py
tm/cli/controller_cli.py
tm/cli/dsl.py
tm/cli/flow.py
tm/cli/fmt.py
tm/cli/intent.py
tm/cli/iterate.py
tm/cli/patch.py
tm/cli/plugin_verify.py
tm/cli/rerun.py
tm/cli/run_cli.py
tm/cli/simulate.py
tm/cli/validate.py
tm/composer/__init__.py
tm/composer/engine.py
tm/composer/reference.py
tm/config/runtime.yaml
tm/connectors/__init__.py
tm/connectors/docker.py
tm/connectors/http_agent.py
tm/connectors/http_schema_v0.md
tm/connectors/k8s.py
tm/connectors/mcp.py
tm/controllers/__init__.py
tm/controllers/cycle.py
tm/controllers/models.py
tm/controllers/builtins/__init__.py
tm/controllers/builtins/act_mock.py
tm/controllers/builtins/decide_llm_stub.py
tm/controllers/builtins/observe_mock.py
tm/controllers/decide/__init__.py
tm/controllers/decide/decide_agent.py
trace_mind-2.0.1.dist-info/METADATA
trace_mind-2.0.1.dist-info/WHEEL
trace_mind-2.0.1.dist-info/entry_points.txt
trace_mind-2.0.1.dist-info/licenses/LICENSE
trace_mind-2.0.1.dist-info/RECORD
