Metadata-Version: 2.4
Name: trace-mind
Version: 2.0.1
Summary: TraceMind smart agent runtime and tooling
Project-URL: Homepage, https://github.com/trace-mind/trace-mind
Project-URL: Documentation, https://github.com/trace-mind/trace-mind/tree/main/docs
Author: TraceMind Authors
License-Expression: MIT
License-File: LICENSE
Classifier: Development Status :: 5 - Production/Stable
Classifier: License :: OSI Approved :: MIT License
Classifier: Operating System :: OS Independent
Classifier: Programming Language :: Python :: 3
Classifier: Programming Language :: Python :: 3.10
Classifier: Programming Language :: Python :: 3.11
Classifier: Programming Language :: Python :: 3.12
Requires-Python: >=3.10
Requires-Dist: fastapi>=0.110.0
Requires-Dist: httpx>=0.27.0
Requires-Dist: jsonschema>=4.10
Requires-Dist: networkx>=3.2
Provides-Extra: cron
Requires-Dist: croniter>=1.4; extra == 'cron'
Provides-Extra: dev
Requires-Dist: black>=23.0; extra == 'dev'
Requires-Dist: mypy>=1.6; extra == 'dev'
Requires-Dist: pytest-cov>=4.1; extra == 'dev'
Requires-Dist: pytest>=8.0; extra == 'dev'
Requires-Dist: ruff>=0.1; extra == 'dev'
Provides-Extra: mcp
Requires-Dist: httpx>=0.25; extra == 'mcp'
Provides-Extra: prom
Requires-Dist: prometheus-client>=0.16; extra == 'prom'
Provides-Extra: retrospect
Requires-Dist: marimo>=0.7; extra == 'retrospect'
Provides-Extra: yaml
Requires-Dist: pyyaml>=6.0; extra == 'yaml'
Requires-Dist: types-pyyaml>=6.0.0; extra == 'yaml'
